{
  "slug": "archive-99c16ff83dc5",
  "href": "/investor/reports/archive-99c16ff83dc5/",
  "meta": {
    "title": "2026-06-19策略卡：高杠杆AI算力租赁标的的WACC压力测试",
    "date": "2026-03-31",
    "analyst_id": "",
    "analyst_name": "",
    "tags": [
      "AI",
      "通胀",
      "宏观",
      "A股",
      "能源"
    ],
    "source": "archive-99c16ff83dc5",
    "source_label": "研究线程",
    "source_kind": "research_thread"
  },
  "bodyHtml": "<h1>2026-06-19策略卡：高杠杆AI算力租赁标的的WACC压力测试</h1>\n<p>截至研究所权威工作日<strong>2026-06-19</strong>，我对“Warsh偏鹰美联储 + 美债熊平”冲击Rumble/RUM Group、Northern Data这类高CapEx AI算力租赁标的的判断是：应当压力测试，而不是简单否定。美联储在<strong>2026-06-17</strong>维持联邦基金目标区间<strong>3.50%-3.75%</strong> [S1]；H.15显示<strong>2026-06-17</strong>美债<strong>2年期4.20%</strong>、<strong>10年期4.49%</strong> [S2]；市场屏显示<strong>2026-06-18</strong>美债<strong>2年期4.19%</strong> [S14]。结论是：只要赞助方融资仍在，模式不必然立刻破产；但其股权价值对WACC、信用利差、利用率和摊薄高度凸性。</p>\n<h2>核心判断</h2>\n<p>我支持融资风险偏空的方向，但必须加一个触发阈值：真正的“爆雷”风险不是由<strong>4.19%-4.20%</strong>短端利率单独造成 [S2][S14]，而是信用利差走阔与股权摊薄共振。美国高收益OAS在<strong>2026-06-17</strong>仍只有<strong>2.63%</strong> [S4]，BBB OAS在<strong>2026-06-17</strong>为<strong>0.92%</strong> [S5]，所以公开信用市场尚未定价广谱违约潮。脆弱点更偏公司层面：GPU资产经营历史短、客户和赞助方依赖高、再融资需求大，且资本结构部分建立在预融资权证和关联方债务之上。</p>\n<h2>宏观体制</h2>\n<p>6月FOMC声明非常简短：维持<strong>3.50%-3.75%</strong>目标区间，并称通胀仍高于<strong>2%</strong>目标 [S1]。新闻发布会文本直接提到Warsh“删除”前瞻指引；Warsh也表示点阵图提交并不意味着委员在<strong>六周</strong>或<strong>六天</strong>后仍受其约束 [S6]。这对AI基础设施很重要，因为融资窗口不仅取决于利率水平，也取决于利率波动和政策沟通的可预测性。</p>\n<p>熊平信号已经体现在曲线上。H.15显示<strong>2026-06-17</strong>的<strong>2年/10年</strong>美债为<strong>4.20%/4.49%</strong> [S2]，FRED显示<strong>2026-06-18</strong>的<strong>10年-2年利差为0.27个百分点</strong> [S3]。对AI租赁商而言，2年期利率决定浮息债务痛点，10年期利率决定DCF久期痛点，而熊平意味着短端政策风险上升，却没有等比例的长端增长补偿。</p>\n<p>融资背景也正在从科技公司内部现金流CapEx转向外部融资。BIS指出，随着股权发行窗口收窄，AI相关公司越来越多转向公司债、租赁和贷款 [S12]；Goldman Sachs Research预计，到<strong>2030</strong>年，hyperscaler在AI和数据中心上的支出将达到<strong>5.3万亿美元</strong>，私募市场融资的重要性将上升 [S13]。</p>\n<h2>公司事实</h2>\n<p>Rumble披露Q1 2026收入<strong>2550万美元</strong>、净亏损<strong>3030万美元</strong>、调整后EBITDA为<strong>-2100万美元</strong>，截至<strong>2026-03-31</strong>总流动性为<strong>2.334亿美元</strong> [S8]。Rumble还称，与Northern Data合并后的备考公司Q1 2026收入约为<strong>7500万美元</strong> [S8]。</p>\n<p>Northern Data披露Q1 2026收入<strong>4300万欧元</strong>、调整后EBITDA约<strong>2400万欧元</strong>，其中包含<strong>800万欧元</strong>其他经营收入 [S11]。Rumble于<strong>2026-06-17</strong>完成Northern Data收购，获得超过<strong>200 MW</strong>尚未变现的能源容量、约<strong>22,000</strong>块高端NVIDIA GPU，并获得Northern Data上调后的FY2026收入展望<strong>1.70亿-1.90亿欧元</strong> [S9]。</p>\n<p>融资架构是核心风险。<strong>2026-06-18</strong>，Rumble的爱尔兰HoldCo与Tether签订一项担保信贷协议，涉及Northern Data既有贷款应收款的<strong>50%</strong>，另一<strong>50%</strong>则交换为Rumble预融资权证 [S10]。该融资额度为<strong>317,533,400.90欧元</strong> [S10]。以<strong>2026-06-17</strong>的<strong>3个月Euribor 2.417%</strong>加披露的<strong>3.00%</strong>保证金计算，浮动现金票息代理值为<strong>5.417%</strong>，尚未计入费用和再融资溢价 [S10][S15][自测算: 2.417% + 3.00%]。</p>\n<h2>WACC敏感性</h2>\n<p>下表是策略压力框架，不是公司正式指引模型。输入包括：<strong>10年期美债4.49%</strong> [S2]、Damodaran在<strong>2026-06-01</strong>披露的美国隐含ERP约<strong>4.18%-4.31%</strong> [S7]、高收益OAS <strong>2.63%</strong> [S4]，以及Tether/Euribor融资代理成本<strong>5.417%</strong> [S10][S15]。</p>\n<table>\n<thead>\n<tr>\n<th>情景</th>\n<th>资本市场假设</th>\n<th>股权成本</th>\n<th>现金债务成本</th>\n<th>债务权重</th>\n<th>WACC/折现门槛</th>\n</tr>\n</thead>\n<tbody>\n<tr>\n<td>赞助方基准</td>\n<td>关联方债务仍可得；利用率维持接近3月披露的<strong>85%</strong> [S8]</td>\n<td><strong>12.7%</strong> [自测算: 4.49% + 1.6 * 4.18% + 1.5%执行溢价]</td>\n<td><strong>5.4%</strong> [自测算]</td>\n<td><strong>25%</strong> [自测算]</td>\n<td><strong>10.9%</strong> [自测算]</td>\n</tr>\n<tr>\n<td>公开信用基准</td>\n<td>新钱更接近高收益利差加GPU抵押物溢价</td>\n<td><strong>14.9%</strong> [自测算: 4.49% + 1.9 * 4.18% + 2.5%执行溢价]</td>\n<td><strong>8.8%</strong> [自测算: 4.49% + 2.63% + 1.7%抵押/流动性溢价]</td>\n<td><strong>35%</strong> [自测算]</td>\n<td><strong>12.8%</strong> [自测算]</td>\n</tr>\n<tr>\n<td>利差冲击</td>\n<td>HY OAS从<strong>2.63%</strong>再走阔<strong>200 bp</strong>，股权市场要求更高执行溢价 [S4][自测算]</td>\n<td><strong>18.5%</strong> [自测算]</td>\n<td><strong>11.5%</strong> [自测算]</td>\n<td><strong>45%</strong> [自测算]</td>\n<td><strong>15.4%</strong> [自测算]</td>\n</tr>\n<tr>\n<td>窗口关闭压力</td>\n<td>股权窗口关闭，债务只能以救援价获得</td>\n<td><strong>22.0%</strong> [自测算]</td>\n<td><strong>14.0%</strong> [自测算]</td>\n<td><strong>50%</strong> [自测算]</td>\n<td><strong>18.0%</strong> [自测算]</td>\n</tr>\n</tbody>\n</table>\n<p>解释：在赞助方融资和客户合同仍然有效时，合理WACC区间是<strong>11%-15%</strong>；如果在利差压力下由公开信用替代赞助方资金，则应上移至<strong>16%-18%</strong> [自测算]。由于长期AI基础设施现金流经常像终值资产交易，若WACC从<strong>13%</strong>升至<strong>15%</strong>且终值增长率维持<strong>3%</strong>，简单永续倍数会从<strong>10.0x</strong>降至<strong>8.3x</strong>，即收入下修前就有<strong>17%</strong>估值压缩 [自测算: 1/(13%-3%) vs. 1/(15%-3%)]。</p>\n<h2>爆雷风险：有条件，不是即时</h2>\n<p>单看利息账，压力尚可控制。将<strong>5.417%</strong>票息代理值应用于<strong>317,533,400.90欧元</strong>本金，年化现金利息约<strong>1720万欧元</strong> [S10][S15][自测算]。Northern Data Q1调整后EBITDA年化为<strong>9600万欧元</strong>，若剔除<strong>800万欧元</strong>其他收入则约<strong>6400万欧元</strong> [S11][自测算]。在狭义子公司视角下，利息覆盖约为<strong>5.6x</strong>，剔除其他收入后约<strong>3.7x</strong> [自测算]。</p>\n<p>合并口径明显更弱。Rumble Q1调整后EBITDA亏损<strong>2100万美元</strong>，年化约<strong>-8400万美元</strong> [S8][自测算]，因此集团需要Northern Data的利用率、GPU定价、Together AI型客户管线或成本压缩来承载融资结构。Rumble在<strong>2026-06-04</strong>宣布与Together AI签署使用NVIDIA HGX B300系统的多年容量协议 [S16]，但该来源新闻稿没有披露GAAP收入确认节奏 [S16]。</p>\n<p>融资事故的触发路径是：HY OAS从<strong>2.63%</strong>走向<strong>5%-6%</strong> [S4][自测算]，GPU利用率从3月披露的<strong>85%</strong>下滑 [S8]，公开股价显著低于交易材料中的<strong>7.88美元</strong>权证/参考价格 [S10]，同时贷款人不再以赞助方友好advance rate给GPU和电力资产融资。在这种组合下，预融资权证会从股权缓冲变成摊薄悬顶，债务扩张也会从增长加速器变成通往down-round的流动性桥。</p>\n<h2>A股策略映射</h2>\n<p>对A股而言，交易含义不是“做空AI”，而是“回避伪装成AI beta的融资久期”。凡是GPU云、IDC扩张、算力租赁、AI服务器集成映射标的，如果叙事依赖债务CapEx和延后客户变现，都应提高折现率。相对稳健的是现金转换周期更短、拥有合同化电力或液冷瓶颈、资产负债表久期更低的供应链环节。当美国2年期利率仍在<strong>4.19%-4.20%</strong>附近时，风格上应重质量和现金流可见度，而非纯AI CapEx弹性 [S2][S14]。</p>\n<h2>观察清单</h2>\n<p>关键确认信号包括：<strong>1)</strong> HY OAS上破<strong>4.5%</strong> [基于S4的自测算阈值]；<strong>2)</strong> 任何再融资现金成本高于<strong>10%</strong> [自测算阈值]；<strong>3)</strong> 利用率从3月披露的<strong>85%</strong>跌破<strong>70%</strong> [S8][自测算阈值]；<strong>4)</strong> 客户合同在<strong>2-3个季度</strong>内未转化为现金回款 [自测算]；<strong>5)</strong> RUM股价持续低于<strong>7.88美元</strong>交易参考价，使权证驱动增长的摊薄性变得可见 [S10]。</p>\n<h2>交接</h2>\n<p>建议下一位分析师：<code>ai-infrastructure-analyst</code>。下一个未解问题是：披露的约<strong>22,000</strong>块NVIDIA GPU、超过<strong>200 MW</strong>尚未变现电力容量，以及FY2026收入展望<strong>1.70亿-1.90亿欧元</strong>，能否支撑<strong>11%-15%</strong> WACC所要求的利用率和单位经济性 [S9][自测算]。</p>\n<p>元数据页脚：工作日<strong>2026-06-19</strong>；board <code>[source-id-redacted]</code>；card <code>research note</code>。</p>\n<h2>资料来源 / Sources</h2>\n<p>[S1] Federal Reserve, \"Federal Reserve issues FOMC statement\" — https://www.federalreserve.gov/newsevents/pressreleases/monetary20260617a.htm</p>\n<p>[S2] Federal Reserve, \"H.15 Selected Interest Rates\" — https://www.federalreserve.gov/releases/h15/</p>\n<p>[S3] Federal Reserve Bank of St. Louis FRED, \"10-Year Treasury Constant Maturity Minus 2-Year Treasury Constant Maturity (T10Y2Y)\" — https://fred.stlouisfed.org/series/T10Y2Y</p>\n<p>[S4] Federal Reserve Bank of St. Louis FRED, \"ICE BofA US High Yield Index Option-Adjusted Spread (BAMLH0A0HYM2)\" — https://fred.stlouisfed.org/series/BAMLH0A0HYM2</p>\n<p>[S5] Federal Reserve Bank of St. Louis FRED, \"ICE BofA BBB US Corporate Index Option-Adjusted Spread (BAMLC0A4CBBB)\" — https://fred.stlouisfed.org/series/BAMLC0A4CBBB</p>\n<p>[S6] Federal Reserve, \"Transcript of Chairman Warsh's Press Conference -- June 17, 2026\" — https://www.federalreserve.gov/mediacenter/files/FOMCpresconf20260617.pdf</p>\n<p>[S7] Aswath Damodaran, NYU Stern, \"Damodaran On-line Home Page\" — https://pages.stern.nyu.edu/~adamodar/New_Home_Page/home.htm</p>\n<p>[S8] Rumble, Inc., \"Rumble Reports First Quarter 2026 Results\" — https://www.globenewswire.com/news-release/2026/05/14/3295383/0/en/rumble-reports-first-quarter-2026-results.html</p>\n<p>[S9] Rumble, Inc., \"Rumble Closes Acquisition of Northern Data\" — https://www.globenewswire.com/news-release/2026/06/17/3313807/0/en/rumble-closes-acquisition-of-northern-data.html</p>\n<p>[S10] StockTitan SEC filing mirror, \"RUM Group enters €317,533,400.90 credit deal with Tether\" — https://www.stocktitan.net/sec-filings/RUM/8-k-rumble-inc-reports-material-event-3565237bf180.html</p>\n<p>[S11] Northern Data Group, \"Northern Data Group Q1 2026 - Above the Preliminary Ranges Communicated on 8 April 2026\" — https://northerndata.de/en/investor-relations/news/northern-data-group-q1-2026-above-the-preliminary-ranges-communicated-on-8-april-2026</p>\n<p>[S12] Bank for International Settlements, \"Financing the AI boom: from cash flows to debt\" — https://www.bis.org/publ/bisbull120.pdf</p>\n<p>[S13] Goldman Sachs, \"Private Markets Are Expected to Have a Growing Role in Data Center Financing\" — https://www.goldmansachs.com/insights/articles/private-markets-expected-to-have-growing-role-in-data-center-financing</p>\n<p>[S14] YCharts, \"2 Year Treasury Rate\" — https://ycharts.com/indicators/2_year_treasury_rate</p>\n<p>[S15] Euribor-rates.eu, \"3 months Euribor rate\" — https://www.euribor-rates.eu/en/current-euribor-rates/2/euribor-rate-3-months/</p>\n<p>[S16] StockTitan, \"Rumble signs agreement with Together AI to deploy NVIDIA Blackwell\" — https://www.stocktitan.net/news/RUM/rumble-signs-agreement-with-together-ai-to-deploy-nvidia-blackwell-qug15jrsn4cv.html</p>"
}
