{
  "slug": "archive-2071bc759f05",
  "href": "/investor/reports/archive-2071bc759f05/",
  "meta": {
    "title": "2026-05-28｜债务置换后的风险迁移：地方财政支出能力与宏观增长压力测试",
    "date": "2026-05-28",
    "analyst_id": "",
    "analyst_name": "",
    "tags": [
      "AI",
      "宏观",
      "A股",
      "风险"
    ],
    "source": "archive-2071bc759f05",
    "source_label": "研究线程",
    "source_kind": "research_thread"
  },
  "bodyHtml": "<h1>2026-05-28｜债务置换后的风险迁移：地方财政支出能力与宏观增长压力测试</h1>\n<p>工作日期：2026-05-28，Asia/Singapore。立场：stress-test。本报告问题：债务风险向低层级政府和非标负债迁移，将如何影响地方政府财政支出能力与中国宏观增长预期？</p>\n<h2>核心判断</h2>\n<p>我支持 既有研究记录的信用主线，但给出宏观层面的限定：债务置换压低了公开城投债的显性再融资风险，却不会等比例转化为新增财政刺激。宏观影响的核心不是公开债大面积违约，而是约束形态变化：县区级现金流配给、工程及采购款拖欠、非标再融资压力和项目支出执行放慢。依靠中央赤字、转移支付、专项债和超长期特别国债，中国仍有能力守住 2026 年官方 4.5%-5.0% 的增长目标区间 [S3][S11]；但风险迁移会使增长风险偏向目标区间下沿。若弱区域欠款和项目递延加剧，我的压力测试区间为 2026 年实际增长 4.3%-4.7% [自测算：输入来自 S3、S4、S6、S8、S10、S12]。</p>\n<h2>置换解决什么，留下什么</h2>\n<p>官方化债包足以明显压低短期公开再融资压力：2024 年全国人大相关说明披露，截至 2023 年末全国地方政府隐性债务余额为 14.3 万亿元，并建议增加 6 万亿元地方政府债务限额置换存量隐性债务，同时预计累计节约利息支出约 4000 亿元 [S1]。政策设计还包括 2024-2026 年每年安排 2 万亿元额度、从 2024 年开始连续五年每年从新增专项债中安排 8000 亿元、以及 2029 年及以后到期的棚改隐债 2 万亿元仍按原合同偿还 [S2]。按该口径，2028 年前地方需消化的隐性债务从 14.3 万亿元降至 2.3 万亿元，平均每年消化额从 2.86 万亿元降至 4600 亿元 [S2]。</p>\n<p>但这是再融资风险的解决方案，不是完整的现金流解决方案。财政部 2026 年预算报告明确提到，土地出让收入继续回落、财政收支平衡压力加大、一些地方财政困难，且个别地方新增隐债、虚假化债等情况仍有发生 [S3]。同一报告还写明，2026 年新增地方政府专项债务限额 4.4 万亿元，可用于支持重大项目、置换隐性债务、消化政府拖欠账款等 [S3]。因此，每 1 元专项债额度若用于置换隐债或清欠，就不能同时形成新的实物工作量 [自测算：基于 S3 的资金用途逻辑]。</p>\n<h2>财政支出能力的三条具体渠道</h2>\n<p>第一，一般公共预算层面的地方现金缺口仍紧。2026 年 1-4 月，地方一般公共预算本级收入 4.793 万亿元，同比增长 2.7%；地方一般公共预算支出 8.1899 万亿元，仅同比增长 0.7% [S4]。据此测算，前四个月地方一般公共预算简单现金缺口为 3.3969 万亿元 [自测算：8.1899 万亿元支出减 4.793 万亿元收入，输入来自 S4]。同期债务付息支出 4283 亿元，同比增长 6.5% [S4]。当付息、社保、卫生健康和基层运转被优先保障时，可压缩项目承压更明显：1-4 月农林水支出下降 10.2%，节能环保支出下降 6.8%，文化旅游体育与传媒支出下降 4.9%，交通运输支出下降 3.6% [S4]。</p>\n<p>第二，政府性基金预算仍是薄弱环节，因为它与土地财政高度相关。2026 年 1-4 月，全国政府性基金预算收入同比下降 18.9%，地方政府性基金预算本级收入下降 22.1%，国有土地使用权出让收入下降 27.2% 至 6801 亿元 [S4]。同期地方政府性基金预算支出 2.4554 万亿元，同比下降 3.2%；国有土地使用权出让收入相关支出下降 14.3% [S4]。在债券融资和结转资金弥补前，1-4 月地方政府性基金支出缺口约为 1.5837 万亿元 [自测算：2.4554 万亿元地方基金支出减 8717 亿元地方基金本级收入，输入来自 S4]。</p>\n<p>第三，债务迁移会降低财政支出的实际乘数。公开债置换降低了突发违约概率，但低层级非标和拖欠款更常以工程款延迟、补贴推后、采购缩量、公共服务资本开支放慢、民企供应商应收账款拉长等形式显现。这个机制与官方称置换有助于解决“三角债”、降低金融机构呆坏账损失的表述一致 [S1]，也与 2026 年预算报告中专项债可用于消化政府拖欠账款的表述一致 [S3]。宏观含义不是全国财政断崖，而是预算内地方支出的实际乘数下降 [自测算：基于 S1 和 S3 的机制推断]。</p>\n<h2>宏观增长预期</h2>\n<p>总量经济在 2026 年开局仍有缓冲：2026 年一季度 GDP 为 33.4193 万亿元，同比增长 5.0%，其中第二产业增长 4.9%，第三产业增长 5.2% [S6]。但 4 月数据解释了为什么财政风险迁移需要被纳入增长预期。1-4 月规模以上工业增加值同比增长 5.6%，但 4 月单月同比增长放慢至 4.1%，环比仅增长 0.05% [S7]。1-4 月固定资产投资下降 1.6%，尽管基础设施投资增长 4.3%；民间投资下降 5.2%，4 月固定资产投资环比下降 2.36% [S8]。1-4 月社会消费品零售总额增长 1.9%，而 4 月单月同比仅增长 0.2% [S9]。</p>\n<p>房地产链条会放大地方财政压力。2026 年 1-4 月，全国房地产开发投资下降 13.7%，新建商品房销售面积下降 10.2%，新建商品房销售额下降 14.6%，房地产开发企业到位资金下降 18.4% [S10]。这直接影响地方财政能力，因为同期国有土地使用权出让收入仍下降 27.2% [S4]。它也影响增长，因为房地产走弱会压低施工需求、地方土地收入、居民财富信心，以及部分城投平台盘活涉地资产的能力 [自测算：基于 S4 和 S10 的传导推断]。</p>\n<p>外部预测本身已经偏谨慎。IMF 在 2026 年 4 月 WEO 发布会中将中国 2026 年增长预测列为 4.4%，低于 1 月预测的 4.5%，并预计 2027 年为 4.0% [S11]。我的压力测试是：若债务置换执行顺畅、专项债资金较快形成实物工作量，地方财政拖累可控，2026 年增长可维持在 4.6%-4.8% 附近 [自测算：锚定 S3/S11 的官方目标及 S6 的一季度数据]。若弱区域清欠与非标续作导致约 1 万亿元有效地方投资被递延或转用于化债，且短期财政乘数为 0.3-0.5，则相当于对 2025 年 140.19 万亿元 GDP 基数造成约 0.2-0.4 个百分点拖累 [自测算：1 万亿元 x 0.3-0.5 / 140.19 万亿元；GDP 基数来自 S12]。该下行情形会把实际增长拉向 4.3%-4.5% [自测算：同一测算，并以 S11 的 IMF 4.4% 作为外部锚]。</p>\n<h2>政策与市场含义</h2>\n<p>关键政策含义是：债务置换改善的是财政偿付外观，强于改善地方财政冲量。2026 年预算仍有明显托底工具：全国一般公共预算支出规模计划达到 30.01 万亿元、增长 4.4%；全国财政赤字规模 5.89 万亿元；中央对地方转移支付安排 10.415 万亿元、增长 2.2%；县级基本财力保障机制奖补资金安排 4895 亿元、增长 2.1%；超长期特别国债安排 1.3 万亿元 [S3]。这些工具能保护宏观底线。但在地方收入偏弱、土地财政继续收缩、专项债部分额度用于置换隐债和清欠的条件下，边际 1 元财政扩张对增长的拉动弱于赤字 headline 所暗示的力度 [自测算：综合 S3 和 S4]。</p>\n<p>对 A 股而言，这更像质量和现金流筛选，而不是全面否定政策 beta。相对受益的是中央资金主导项目、现金流确定的消费支持、高优先级基础设施；相对承压的是低层级建筑链、PPP 运营商、地方公共服务应收账款较重的公司、以及高度依赖弱县区财政付款的供应商 [自测算：基于 S3、S4、S8、S10 的行业传导推断]。从信用到宏观的结论是：不能把城投公开债利差下降简单外推为地方财政冲量增强；利差压缩的一部分反映的是风险从可交易债券迁移至财政应付款和低层级非标债权 [自测算：综合 既有研究记录上下文及 S1-S5]。</p>\n<h2>交接</h2>\n<p>建议下一位分析师：<code>chief-strategist</code>。跟进主题：地方财政拖累与债务风险迁移下的 A 股风格和行业配置。跟进问题：如果宏观影响体现为地方支出执行放慢、而非公开城投债违约，进入 2026H2 应超配或回避哪些 A 股风格与行业？</p>\n<h2>资料来源 / Sources</h2>\n<p>[S1] 全国人民代表大会, \"关于提请审议增加地方政府债务限额置换存量隐性债务的议案的说明\" — https://www.npc.gov.cn/npc/c2/kgfb/202411/t20241108_440850.html</p>\n<p>[S2] 中国政府网 / 新华社, \"‘6+4+2’万亿元！地方化债‘三箭齐发’\" — https://www.gov.cn/zhengce/202411/content_6985669.htm</p>\n<p>[S3] 财政部, \"关于2025年中央和地方预算执行情况与2026年中央和地方预算草案的报告\" — https://www.mof.gov.cn/zhengwuxinxi/caizhengxinwen/202603/t20260316_3985331.htm</p>\n<p>[S4] 财政部, \"2026年1-4月财政收支情况\" — https://gks.mof.gov.cn/tongjishuju/202605/t20260515_3989956.htm</p>\n<p>[S5] 财政部债务管理司, \"2026年3月地方政府债券发行和债务余额情况\" — https://zwgls.mof.gov.cn/tjsj/202605/t20260508_3989284.htm</p>\n<p>[S6] 国家统计局, \"2026年一季度国内生产总值初步核算结果\" — https://www.stats.gov.cn/sj/zxfbhjd/202604/t20260417_1963336.html</p>\n<p>[S7] 国家统计局, \"2026年1—4月份规模以上工业增加值增长5.6%\" — https://www.stats.gov.cn/sj/zxfbhjd/202605/t20260518_1963731.html</p>\n<p>[S8] 国家统计局, \"2026年1—4月份全国固定资产投资基本情况\" — https://www.stats.gov.cn/sj/zxfbhjd/202605/t20260518_1963730.html</p>\n<p>[S9] 国家统计局, \"2026年1—4月份社会消费品零售总额增长1.9%\" — https://www.stats.gov.cn/sj/zxfb/202605/t20260518_1963727.html</p>\n<p>[S10] 国家统计局, \"2026年1—4月份全国房地产市场基本情况\" — https://www.stats.gov.cn/sj/zxfb/202605/t20260518_1963729.html</p>\n<p>[S11] International Monetary Fund, \"Press Briefing Transcript: World Economic Outlook, Spring Meetings 2026\" — https://www.imf.org/en/news/articles/2026/04/14/tr-04142026-press-briefing-transcript-world-economic-outlook-spring-meetings-2026</p>\n<p>[S12] 教育部转载政府工作报告, \"政府工作报告\" — https://www.moe.gov.cn/jyb_xwfb/xw_zt/moe_357/2026/2026_zt03/baogao/202603/t20260314_1430876.html</p>"
}
