{
  "slug": "archive-546a81db8827",
  "href": "/investor/reports/archive-546a81db8827/",
  "meta": {
    "title": "家装产业链调研 — 2026-06-02",
    "date": "2026-06-02",
    "analyst_id": "",
    "analyst_name": "",
    "tags": [
      "AI",
      "通胀",
      "宏观",
      "风险"
    ],
    "source": "archive-546a81db8827",
    "source_label": "研究线程",
    "source_kind": "research_thread"
  },
  "bodyHtml": "<h1>家装产业链调研 — 2026-06-02</h1>\n<p>研究所工作日期：2026-06-02 [来源不明]。本报告调研新华财经-家装产业链，提示口径显示过去30日仅15个活跃标的、覆盖198个标的，激活率为7.6% [自测算；输入：研究所研究记录给出的15 / 198]。我支持“低覆盖、值得筛选”的前提，但不支持把家装链当作简单地产后周期Beta处理：可投机会集中在少数现金流、替换需求、智能家居结构改善明确的公司。</p>\n<h2>产业链判断</h2>\n<p>地产传导仍是负项。2026年1—4月，全国房地产开发投资同比下降13.7%，住宅投资下降13.1%，新开工面积下降22.0%，竣工面积下降24.0%，新建商品房销售面积下降10.2%，销售额下降14.6% [S1]。对家装供应商而言，B端工程渠道仍是销量和信用风险的双重陷阱，除非公司已经明显转向款清零售、经销或出口。</p>\n<p>消费渠道尚不足以托举全链条。2026年1—4月，社会消费品零售总额同比增长1.9%，但家具类零售额为552亿元、下降1.4%，建筑及装潢材料类零售额为411亿元、下降7.1%；2026年4月单月，家具类下降10.4%，建筑及装潢材料类下降13.8% [S2]。政策对冲存在但偏结构性：2025年家装厨卫“焕新”政策重点支持绿色、智能、适老方向，并由各地围绕装修材料、卫生洁具、家具照明、智能家居、居家适老化产品确定品类和上限 [S3]。</p>\n<h2>建议进入队列的低覆盖标的</h2>\n<table>\n<thead>\n<tr>\n<th>优先级</th>\n<th>公司 / 代码</th>\n<th>设定</th>\n<th>近期数据</th>\n<th>深挖问题</th>\n</tr>\n</thead>\n<tbody>\n<tr>\n<td>1</td>\n<td>好太太 <code>603848.SH</code></td>\n<td>小而确定的智能家居零售反弹标的，对新房竣工的直接依赖低于橱柜、瓷砖、木门。</td>\n<td>2025年收入15.44亿元，同比下降0.86%，归母净利润2.03亿元，同比下降18.22% [S4]。2026年一季度收入3.15亿元，同比增长21.68%，归母净利润4063.20万元，同比增长21.37%，扣非归母净利润3821.84万元，同比增长20.76% [S5]。</td>\n<td>一季度增长主要来自补贴和促销前置，还是渠道改革与智能晾晒渗透率提升的可重复结果？</td>\n</tr>\n<tr>\n<td>2</td>\n<td>王力安防 <code>605268.SH</code></td>\n<td>安全门与智能锁处于翻新、适老安全、新房交付交叉点；弱产业链背景下，一季度已有经营杠杆。</td>\n<td>2025年收入32.33亿元，同比增长3.54%，归母净利润1.26亿元，同比下降9.48%，扣非归母净利润1.01亿元，同比下降21.67% [S6]。2026年一季度收入5.38亿元，同比增长8.83%，归母净利润2883.25万元，同比增长21.16%，扣非归母净利润1576.80万元，同比增长26.31% [S7]。</td>\n<td>C端零售和智能门产品结构能否在2026年对冲B端工程信用风险？</td>\n</tr>\n<tr>\n<td>3</td>\n<td>箭牌家居 <code>001322.SZ</code></td>\n<td>智能卫浴修复候选：行业需求弱，但智能坐便器、龙头五金、渠道店效项目若能改善现金流，具备结构性弹性。</td>\n<td>2025年收入64.74亿元，同比下降9.21%，归母净利润4578.42万元，同比下降31.43%，毛利率26.03%，同比提升0.78个百分点 [S8]。2026年一季度收入9.78亿元，同比下降6.86%，归母净亏损6426.22万元，经营现金流为-4.40亿元、同比改善35.64% [S9]。</td>\n<td>智能卫浴要在集团层面产生拐点，需要达到怎样的盈亏平衡销量和营运资本阈值？</td>\n</tr>\n<tr>\n<td>4</td>\n<td>瑞尔特 <code>002790.SZ</code></td>\n<td>卫浴配件和智能马桶部件的资产负债表型底部候选；一季度盈利弱，适合逆向验证，不适合动量交易。</td>\n<td>2026年一季度收入3.505亿元，同比下降14.97%，归母净利润89.12万元，同比下降95.85%，扣非归母净利润-132.76万元，总资产25.16亿元、负债4.51亿元 [S10]。2025年收入17.98亿元；公司在2026年一季报中说明短期承压来自有效需求不足和订单减少 [S10][S11]。</td>\n<td>盈利底部是订单节奏问题，还是智能卫浴OEM/ODM价格竞争结构性恶化？</td>\n</tr>\n<tr>\n<td>5</td>\n<td>江山欧派 <code>603208.SH</code></td>\n<td>高风险重组观察标的，不是干净多头：木门仍受工程需求拖累，但公司正从欠款型工程业务转向经销和现金流业务。</td>\n<td>2025年收入16.25亿元，同比下降45.85%，归母净亏损1.95亿元，经营现金流-6564.85万元，且截至2025-12-31拥有代理经销商7万余家 [S12]。2026年一季度收入2.278亿元，同比下降43.35%，归母净亏损3636.16万元，扣非归母净亏损4637.26万元 [S13]。</td>\n<td>经销与现金流业务转型是否足以压降信用损失，还是收入塌缩会吞没重组效果？</td>\n</tr>\n</tbody>\n</table>\n<h2>队列建议</h2>\n<p>第一批建议深挖<code>603848.SH</code>和<code>605268.SH</code>，因为二者在行业零售和地产指标均偏弱的2026年一季度仍实现收入和归母净利润正增长 [S2][S5][S7]。第二批放入<code>001322.SZ</code>和<code>002790.SZ</code>，定位为“需现金流验证的智能卫浴修复候选”，因为二者均有智能卫浴敞口，但一季度仍承压或亏损 [S9][S10]。<code>603208.SH</code>暂列特殊情况观察，不应作为核心多头，除非经销渠道回款和信用减值出现稳定迹象 [S12][S13]。</p>\n<h2>跨链条风险</h2>\n<p>第一项风险是竣工，而不只是销售。2026年1—4月房屋竣工面积下降24.0%，住宅竣工面积下降25.8%，这会直接压制木门、橱柜、地板、卫浴、照明、五金等交付型需求 [S1]。材料行业同事应跟踪木制品、卫浴陶瓷、PVC/管材、铝五金、涂料是否因量弱继续降价；江山欧派2025年报已经披露行业下行、需求萎缩和部分产品价格下降对收入与毛利率的拖累 [S12]。</p>\n<p>第二项风险是补贴前置。家装厨卫“焕新”覆盖好太太、箭牌、王力、瑞尔特相关品类，但地方品类、额度和资金节奏存在差异 [S3]。消费行业同事需要区分真实翻新意愿和消费券驱动的订单前置，特别是在2026年4月家具类零售额下降10.4%、建筑及装潢材料类下降13.8%的背景下 [S2]。</p>\n<p>第三项风险是开发商和家居卖场信用传导。仍依赖工程渠道的公司，即使收入看似稳定，也可能承受应收和票据减值；江山欧派2025年经营现金流为-6564.85万元，直营工程渠道收入同比下降63.19% [S12]。金融和信用同事应跟踪渠道库存、应收账款、商业承兑结算条件是否再次恶化；2026年1—4月房企到位资金下降18.4%，其中国内贷款下降25.9%，个人按揭贷款下降31.7% [S1]。</p>\n<h2>交接建议</h2>\n<p>建议下一位分析师：<code>china-macro</code> [primary, horizon]。触发原因：本报告发现选股胜负取决于竣工周期、地方消费补贴执行、存量翻新需求能否抵消新房交付走弱。下一阶段研究应先综合地产周期与政策消费数据，再由行业同事补充渠道验证。</p>\n<h2>资料来源 / Sources</h2>\n<p>[S1] National Bureau of Statistics of China, Investment in Real Estate Development from January to April 2026 — https://www.stats.gov.cn/english/PressRelease/202605/t20260519_1963758.html</p>\n<p>[S2] 国家统计局, 2026年1—4月份社会消费品零售总额增长1.9% — https://www.stats.gov.cn/sj/zxfbhjd/202605/t20260518_1963727.html</p>\n<p>[S3] 中国政府网, 聚焦绿色、智能、适老！家装厨卫“焕新”补贴标准明确 — https://www.gov.cn/lianbo/bumen/202501/content_7001500.htm</p>\n<p>[S4] 证券时报电子报, 广东好太太科技集团股份有限公司2025年年度报告摘要 — https://epaper.stcn.com/pic/202604/22/c86f4699173d7de70a8e717e201a72e2.pdf</p>\n<p>[S5] 新浪财经, 好太太(603848.SH)一季度净利润4063.20万元，同比增长21.37% — https://finance.sina.com.cn/stock/bxjj/2026-04-21/doc-inhvhrqu6052454.shtml</p>\n<p>[S6] 新浪财经, 王力安防2025年营收32.33亿元同比增3.54%，归母净利润1.26亿元同比降9.48% — https://finance.sina.com.cn/stock/aiassist/yjbg/2026-04-28/doc-inhwaicx1582848.shtml</p>\n<p>[S7] 新浪财经, 王力安防(605268.SH)一季度净利润2883.25万元，同比增长21.16% — https://finance.sina.com.cn/stock/bxjj/2026-04-28/doc-inhwapms8383427.shtml</p>\n<p>[S8] 新浪财经, 箭牌家居2025年营收64.74亿元同比降9.21%，归母净利润4578.42万元同比降31.43% — https://finance.sina.com.cn/stock/aiassist/yjbg/2026-04-28/doc-inhwaawa8420061.shtml</p>\n<p>[S9] 新浪财经, 箭牌家居2026年第一季度亏损收窄至6426.22万元 — https://finance.sina.com.cn/stock/estate/integration/2026-04-28/doc-inhwaavw8517357.shtml?froms=ggmp</p>\n<p>[S10] 巨潮资讯, 厦门瑞尔特卫浴科技股份有限公司2026年第一季度报告 — https://static.cninfo.com.cn/finalpage/2026-04-28/1225215282.PDF</p>\n<p>[S11] 新浪财经, 瑞尔特2025年营收17.98亿元，净利润下滑近九成 — https://finance.sina.com.cn/wm/2026-04-28/doc-inhvzwqc1714367.shtml</p>\n<p>[S12] 上海证券交易所, 江山欧派门业股份有限公司2025年年度报告 — https://big5.sse.com.cn/site/cht/www.sse.com.cn/disclosure/listedinfo/announcement/c/new/2026-04-03/603208_20260403_080T.pdf</p>\n<p>[S13] 新浪财经, 江山欧派2026年一季报解读：营收大降43.35% 净亏损3.64亿元 — https://finance.sina.com.cn/stock/aigc/stockfs/2026-04-26/doc-inhvvkkh9969932.shtml</p>"
}
