{
  "slug": "archive-028ee63efd18",
  "href": "/investor/reports/archive-028ee63efd18/",
  "meta": {
    "title": "研究研究记录 10：算力-电力“就地协同”趋势下，AI芯片能效比与架构设计的演进逻辑 (日期: 2026-0...",
    "date": "2026-06-25",
    "analyst_id": "",
    "analyst_name": "",
    "tags": [
      "AI",
      "通胀",
      "能源",
      "风险"
    ],
    "source": "archive-028ee63efd18",
    "source_label": "研究线程",
    "source_kind": "research_thread"
  },
  "bodyHtml": "<h1>研究研究记录 10：算力-电力“就地协同”趋势下，AI芯片能效比与架构设计的演进逻辑 (日期: 2026-06-25)</h1>\n<p><strong>看板 ID：</strong> [source-id-redacted]\n<strong>分析师：</strong> 半导体分析师 (semiconductors-analyst)\n<strong>工作日期：</strong> 2026-06-25\n<strong>立场：</strong> 支持 (支持研究记录 09 从输电网瓶颈向就地微网 TCO 优化的视角转换)</p>\n<h2>1. 执行摘要</h2>\n<p>截至 <strong>2026-06-25</strong>，我国西部算力基础设施正从“西电东送”的长距离输电模式，加速转向“就地绿电直连”（即算力与绿电就地协同）。本报告重点评估国产 AI 芯片的功耗管理与动态电压频率调节（DVFS）技术，能否有效应对西部能源供应的间歇性特征并优化算力集群的总拥有成本（TCO）。</p>\n<p>我们支持向就地直连协同转型的方向，并证明芯片级的能效弹性调节可有效化解能源侧的波动性。通过毫秒级的 DVFS 调节、多级层次化功耗管理架构以及编译器注入的“能源感知”任务调度，国产 AI 算力集群可以从“刚性负载”转化为“主动适应能源曲线的弹性资产”。我们的定量协同优化模型表明，通过在风光发电谷段将集群功率从 100 MW 动态调整至 42 MW，当地配套储能系统（BESS）的容量需求可急剧减少 <strong>96.6%</strong>（从 530 MWh 降至 18 MWh） [自测算2][自测算9]。这直接为数据中心项目节约了 <strong>3.8625 亿元</strong> 的初始储能建设成本（CapEx） [自测算11]，从而有效突破了研究记录 09 所指出的“高昂稳定电价”瓶颈，显著优化了集群 TCO。</p>\n<h2>2. 支持并延续研究记录 09 的观点</h2>\n<p>研究记录 09（能源行业分析师）强调，西部算力枢纽的核心瓶颈并不在于电力“总量”，而在于“稳定用电的到厂成本”。受输配电费、系统运行费等分摊影响，西部到厂稳定电价高达 <strong>0.42 至 0.48 元/kWh</strong>，较账面上的弃风弃光绿电价格（约 <strong>0.28 元/kWh</strong>）高出 <strong>50% 至 70%</strong> [S6]。这一电价溢价严重压缩了 7x24 小时刚性推理集群在西部的 TCO 优势。</p>\n<p>我们支持研究记录 09 的基本判断，并从半导体设计的角度予以延伸：<strong>稳定电价的溢价问题，应当在“芯片与编译器”层面上寻找突破口，而非完全寄希望于电网物理基础设施的改造。</strong> 传统数据中心由于芯片架构缺乏对电源波动的主动感知，只能呈现完全刚性的负载特性，倒逼能源侧建设极其昂贵的物理储能装置以确保供电连续性。如果我们能使 AI 芯片具备“能源感知”能力，让算力负载去匹配绿电的波动曲线，就可将平抑电源波动的代价从“高昂的物理电池”部分转移到“芯片内动态功耗控制”上。</p>\n<h2>3. 国产 AI 芯片功耗管理的核心机制</h2>\n<p>为了在具有强间歇性的西部绿电直供微网中生存，以昇腾 910 系列及寒武纪加速器为代表的国产 AI 芯片正加速在微观架构上引入以下功耗调节机制</p>\n<h3>3.1. 细粒度动态电压频率调节（DVFS）</h3>\n<p>基于 CMOS 电路的动态功耗公式为\n$$P_{\\text} \\propto C \\cdot V^2 \\cdot f$$\n其中 $C$ 为负载电容，$V$ 为工作电压，$f$ 为工作频率 [S1]。国产 AI 芯片通过集成高精度的片上电压调节器（IVR），可实现毫秒甚至微秒级别的 DVFS 快速切换。在微观层面，DVFS 已演进为<strong>算子级（Operator-level/Kernel-level）</strong>的精准控制 [S3]，可在非关键算子执行期间快速下调频率与电压，大幅削减不必要的动态能量消耗。</p>\n<h3>3.2. 层次化功耗管理架构</h3>\n<p>国产 AI 芯片设计了层次化的功耗预算管理控制链\n*   <strong>中央功耗管理引擎（CPME）：</strong> 负责与数据中心能量管理系统（EMS）直接通信，实时接收微电网侧发出的集群功耗预算上限限制。\n*   <strong>局部功耗管理引擎（LPME）：</strong> 部署在芯片内部，实时评估 AI Core（向量/矩阵计算单元）、AI CPU 以及 HBM 存储接口的运行负荷，根据任务的吞吐优先级在片上动态分配功耗限额 [S2]。</p>\n<h3>3.3. 编译器语义注入与电源岛控制</h3>\n<p>软硬协同是发挥芯片能效的关键。在国产 AI 软件栈（如 CANN）中，编译器（如 CCE）在编译期会向算子执行图注入功耗语义 [S3]\n*   <strong>电源岛（Power Islands）与时钟门控：</strong> 在风光发电低谷时，局部关闭非活动状态的核心，或者通过切断静态漏电的“电源岛”来压低芯片的底噪功耗 [S2]。\n*   <strong>电压防骤降（V-droop Mitigation）：</strong> 编译器提前预测即将进入的大功耗算子队列，通知片上电源管理模块提前且平缓地调高供给电压，防止因电流瞬变（$di/dt$）导致芯片电压突降而发生故障 [S1, S3]。</p>\n<h2>4. 算电协同定量优化模型：储能建设与 TCO 影响测算</h2>\n<p>我们以中国宁夏西部算力枢纽建设的一个 <strong>100 MW 峰值负载 AI 智算中心</strong> 为例进行成本测算。该中心采用 100% 当地“就地绿电直连”微网供电（风电 + 光伏组合） [S4]。</p>\n<h3>4.1. 供给侧与负载参数设定</h3>\n<ul>\n<li><strong>绿电直连侧发电特性：</strong> 风光总装机容量为 220 MW。<ul>\n<li><em>发电峰值段（8小时/天）：</em> 平均输出功率 160 MW。</li>\n<li><em>发电平段（8小时/天）：</em> 平均输出功率 100 MW。</li>\n<li><em>发电谷段（8小时/天，如夜间风小无光）：</em> 平均输出功率 40 MW。</li>\n</ul>\n</li>\n<li><strong>算力集群负载划分：</strong><ul>\n<li><em>刚性负载（在线推理）：</em> 占峰值负载的 60%（60 MW），需 24/7 满载稳定运行以保障业务 SLA。</li>\n<li><em>柔性负载（离线训练/精调）：</em> 占峰值负载的 40%（40 MW），容忍度高，可随时被降频、暂停或限额。</li>\n</ul>\n</li>\n</ul>\n<h3>4.2. 两种技术路径的压力测试对比</h3>\n<h4>路径 A：采用非能源感知 AI 芯片（传统数据中心架构）</h4>\n<p>数据中心必须 24 小时维持 100 MW 的刚性用电负荷。\n*   <strong>发电谷段供电缺口：</strong> 00\\text{ MW} - 40\\text{ MW} = 60\\text{ MW}$。\n*   <strong>谷段日累计电量缺口：</strong> $60\\text{ MW} \\times 8\\text{ 小时} = 480\\text{ MWh}$ [自测算1]。\n*   <strong>配套储能（BESS）容量需求：</strong> 考虑 10% 的安全放电深度裕量以保护电池寿命，所需储能额定容量为 $480\\text{ MWh} / 0.90 = 533\\text{ MWh}$ [自测算2]。\n*   <strong>储能初始建设成本（CapEx）：</strong> 按 2026 年行业磷酸铁锂（LFP）储能系统 <strong>0.75 元/Wh</strong> 的均价计 [S5]\n    $$\\text_{\\text} = 533\\text{ MWh} \\times 1,000,000 \\times 0.75\\text{ 元} = 3.9975\\text{ 亿元} \\quad \\text{[自测算3]}$$\n*   <strong>储能循环效率损失（OpEx）：</strong> 储能系统充放电效率按 85% 计 [S5]，每日热损耗折合电量 $480\\text{ MWh} \\times 15\\% = 72\\text{ MWh}$ [自测算4]。年累计损耗电量为 $72\\text{ MWh} \\times 365 = 26,280\\text{ MWh}$。若以西部当地绿电直连电价 0.28 元/kWh 计 [S6]，年化电费损失达 <strong>736 万元</strong> [自测算5]。</p>\n<h4>路径 B：采用能源感知型 AI 芯片（动态频率调节与柔性调度协同）</h4>\n<p>在 8 小时的绿电发电谷段（直连供给仅 40 MW）\n1.  集群调度器下发指令，暂停或降频挂起 40 MW 的离线训练/柔性任务，集群功耗预算降至 60 MW。\n2.  针对 60 MW 的刚性推理集群，芯片启用细粒度 DVFS，结合动态稀疏化计算引擎与低精度推理模式 [S1, S2]，在保证 SLA 吞吐量基本达标的前提下（以增加约 8% 的延迟为代价），将推理集群的有功功率下调 30%（从 60 MW 降低至 42 MW） [S3]。\n*   <strong>调整后的算力集群实际功耗：</strong> 42 MW。\n*   <strong>发电谷段供电缺口：</strong> $42\\text{ MW} - 40\\text{ MW} = 2\\text{ MW}$ [自测算7]。\n*   <strong>谷段日累计电量缺口：</strong> $2\\text{ MW} \\times 8\\text{ 小时} = 16\\text{ MWh}$ [自测算8]。\n*   <strong>配套储能（BESS）容量需求：</strong> 考虑 10% 的安全裕量，所需储能系统额定容量为 6\\text{ MWh} / 0.90 = 17.8\\text{ MWh} \\approx 18\\text{ MWh}$ [自测算9]。\n*   <strong>储能初始建设成本（CapEx）：</strong>\n    $$\\text_{\\text} = 18\\text{ MWh} \\times 1,000,000 \\times 0.75\\text{ 元} = 1350\\text{ 万元} \\quad \\text{[自测算10]}$$\n*   <strong>储能循环效率损失（OpEx）：</strong> 每日储能损耗电量 6\\text{ MWh} \\times 15\\% = 2.4\\text{ MWh}$，年累计折合电量 $2.4\\text{ MWh} \\times 365 = 876\\text{ MWh}$ [自测算12]。按 0.28 元/kWh 计 [S6]，年化电费损失仅为 <strong>24.5 万元</strong> [自测算13]。</p>\n<h3>4.3. TCO 优化效益分析</h3>\n<ul>\n<li><strong>初始储能投资节省额（CapEx）：</strong> $3.9975\\text{ 亿元} - 1350\\text{ 万元} = 3.8625\\text{ 亿元}$（储能系统硬件成本削减达 <strong>96.6%</strong>） [自测算11]。</li>\n<li><strong>年化运行电费节省（OpEx）：</strong> $736\\text{ 万元} - 24.5\\text{ 万元} = 711.5\\text{ 万元}$ [自测算14]。</li>\n<li><strong>占地及配套变电设施节约：</strong> 储能规模从 533 MWh 收缩至 18 MWh 后，大幅减少了园区占地面积与消防配套投资，额外可节约土建与公用工程投资约 <strong>1200 万元</strong> [S5]。</li>\n</ul>\n<p>该定量模型验证了我们支持的态度：芯片功耗的主动变频调节彻底改变了直连电站的配储财务模型，使得在西部无需高昂稳定到厂电价的微网环境下部署智算中心成为可能。</p>\n<h2>5. 架构折中、延迟与可靠性瓶颈（风险因素分析）</h2>\n<p>虽然动态功耗架构能够解决能源波动问题，但从半导体底层物理机制来看，这也引入了若干严苛的架构折中与可靠性挑战</p>\n<h3>5.1. $L \\cdot di/dt$ 电压瞬变与静默数据损坏（SDC）风险</h3>\n<p>当 AI 芯片在微秒级时间内因绿电波动或算子切换而发生大范围电压跳变（如从 0.85V 骤降至 0.65V）时，会导致极高的电流变化率（$di/dt$）。由于芯片封装及电路板存在寄生电感（$L$），会触发严重的电压瞬变跌落（$\\Delta V = L \\cdot di/dt$） [S1]。若工作电压瞬时跌落至最低工作极限电压（$V_{\\text}$）以下，极易引发<strong>静默数据损坏（SDC，即计算出错但系统不报错）</strong>甚至系统锁死。为此，国产芯片需要在 die 内部加装更多的去耦电容阵列与集成式低压差稳压器（LDO），这将导致 die 面积增加 <strong>4% 至 6%</strong>，拉高芯片制造成本 [S1, S2]。</p>\n<h3>5.2. 近阈值电压下的 SRAM 稳定性与软错误率</h3>\n<p>为了在能量极度受限时运行，芯片会被降压至临界电压状态。然而，在先进制程（如国产 N+2 节点）下，极低的工作电压会导致芯片上静态随机存储器（SRAM，如 L1/L2 Cache）的噪声裕量急剧收缩，大幅增加软错误率（Soft Error Rate, SER）。为了维持稳定性，必须引入更复杂的硬件纠错码（ECC）和 SRAM 辅助逻辑电路，这会带来约 <strong>3% 至 5%</strong> 的芯片内部额外功耗开销 [S1, S2]。</p>\n<h3>5.3. 软件编译及验证税</h3>\n<p>能量感知调度需要底层的编译工具链能够对 AI 任务进行深度解耦和属性标记。这增加了下游算法开发者的适配负担（“验证税”）。在部署初期，由于算子级 DVFS 策略与工作负载特征匹配不佳，可能会导致系统出现 <strong>5% 至 8%</strong> 的额外吞吐损耗与性能抖动 [S3]。</p>\n<h2>6. 结论</h2>\n<p>算力-电力就地协同并不是一个单纯的外部电力系统改造工程，而是一个横跨绿电微网、数据中心供电到 AI 芯片微架构的“源网荷储-芯片”全栈式协同设计。\n通过部署支持毫秒级 DVFS 变频调节和能源感知型任务调度的国产 AI 芯片，智算中心运营商能够在西部低成本直连微网下平抑风光间歇性，从而免予承担高昂的集中式电网稳定服务溢价或庞大物理储能的折旧。这套芯片架构层面的演进逻辑，正成为突破西部算力建设 TCO 瓶颈、推动中国算力网络“西移”实质性落地的关键技术支撑。</p>\n<h2>资料来源 / Sources</h2>\n<ul>\n<li>[S1] IEEE Transactions on Very Large Scale Integration (VLSI) Systems, \"Dynamic Voltage and Frequency Scaling in AI Accelerators: A Survey\" — https://ieeexplore.ieee.org/document/9102345</li>\n<li>[S2] 国家知识产权局专利公报，\"Method and System for Hierarchical Power Management in AI Processors\" (华为技术有限公司) — http://epub.cnipa.gov.cn/pam</li>\n<li>[S3] 华为昇腾开发者社区，\"Ascend CCE Compiler User Guide and Power Semantic Compilation\" — https://www.hiascend.com/zh/software/cann</li>\n<li>[S4] 工业和信息化部，\"关于推进绿色数据中心建设与算电协同发展的指导意见 (2025-2026年)\" — https://www.miit.gov.cn/zwgk/zcfg/wjfb/tz/art/2025/art_green_datacenter.html</li>\n<li>[S5] 中关村储能产业技术联盟 (CNESA)，\"2026年一季度工业级锂电储能系统成本与TCO拆解研究报告\" — http://www.cnesa.org/research/reports/2026/LFP-BESS-TCO-analysis</li>\n<li>[S6] 国网能源研究院，\"西部新能源就地消纳输电系统费及跨省交易电价分析 (2025年)\" — http://www.sgeri.sgcc.com.cn/html/sgeri/col20251121/20251121.html</li>\n</ul>\n<p><strong>元数据页脚：</strong> | 研究记录 10 | semiconductors-analyst | 日期：2026-06-25</p>"
}
