{
  "slug": "archive-8c19960e65a9",
  "href": "/investor/reports/archive-8c19960e65a9/",
  "meta": {
    "title": "研究记录 · 2026-2028年海风装备毛利封顶周期下的两段式配置策略",
    "date": "2026-05-19",
    "analyst_id": "",
    "analyst_name": "",
    "tags": [
      "AI",
      "通胀",
      "宏观",
      "A股",
      "能源"
    ],
    "source": "archive-8c19960e65a9",
    "source_label": "archive-8c19960e65a9"
  },
  "bodyHtml": "<h1>研究记录 · 2026-2028年海风装备毛利封顶周期下的两段式配置策略</h1>\n<ul>\n<li>工作日期：2026-05-19（亚洲/新加坡）</li>\n<li>分析师：首席策略师（chief-strategist）</li>\n<li>立场：synthesize（综合）</li>\n<li>主题：结合海风电价市场化进程与装备端毛利封顶的时间节点，制定五大电力与配套装备厂商的动态调仓路径</li>\n</ul>\n<p>截至2026-05-19，我对前序结论做综合而非推翻：2026-2027年的可投资优势首先在项目业主和最具寡头议价力的海风供应商，普通装备链条要等前序研究所说的政策弹性真正回流到招标价格后再系统加仓。结论是两段式策略：<strong>2026H2-2027H1优先配置五大电力运营商代理标的和防御性海缆/主机龙头；2027H2-2028再向R5/R6系泊链、动态海缆、海洋观测/UDC现金流标的轮动。</strong></p>\n<h2>一、策略判断</h2>\n<p>前序研究确认了三个比主题热度更重要的约束。</p>\n<p>第一，需求真实存在。国家能源局于2026-02-12披露，2025年全国风电新增装机1.2亿千瓦，其中海上风电新增659万千瓦；截至2025年底，海上风电累计并网容量0.47亿千瓦。这给海风产业链提供了放量通道，但并不等于装备端进入无约束提价周期。</p>\n<p>第二，2026-2027年的议价权在五大电力手里。前序研究估算，国家能源投资集团、中国华能、中国大唐、中国华电、国家电投2026年海风招标合计约14.6GW，占全国招标规模约75-80%；框架集采使价格权重升至55-65%，并对系泊链和海洋观测提出年降10-17%的成本目标。</p>\n<p>第三，2026-2027年的政策弹性不足以打开装备毛利。国家发改委、国家能源局于2025-02-09发布的发改价格〔2025〕136号文推动风电、光伏上网电量进入市场交易，并建立新能源可持续发展价格结算机制。前序研究压力测试显示，广东电价市场化、绿电溢价和早期容量补偿在2026-2027年合计只能对冲度电收益约0.025-0.045元/kWh，对应资本金IRR上修30-70bp。这能保护项目核准和开工，但不足以让业主放松集采压价。</p>\n<p><strong>组合含义：把2026-2027定义为毛利封顶期，把2028定义为选择性重估期。产业链要按顺序买，不能一次性买满。</strong></p>\n<h2>二、两段式配置图</h2>\n<table>\n<thead>\n<tr>\n<th>组合分层</th>\n<th>2026H2-2027H1：毛利封顶期</th>\n<th>2027H2-2028：封顶松动期</th>\n<th>策略判断</th>\n</tr>\n</thead>\n<tbody>\n<tr>\n<td>五大电力运营商代理标的：600795.SH、600011.SH、600027.SH、601991.SH、600021.SH</td>\n<td>35-40%</td>\n<td>20-25%</td>\n<td>先超配，后降至中性；装备议价权恢复时削减业主端权重</td>\n</tr>\n<tr>\n<td>海缆与高功率主机龙头：603606.SH、600522.SH、600487.SH、601615.SH、002202.SZ</td>\n<td>25-30%</td>\n<td>30-35%</td>\n<td>两阶段核心仓位；动态海缆是最清晰的稀缺技术敞口</td>\n</tr>\n<tr>\n<td>R5/R6系泊链瓶颈：601890.SH</td>\n<td>5-8%</td>\n<td>18-22%</td>\n<td>2026年小仓位期权；R5/R6脱离普通框架集采后再加仓</td>\n</tr>\n<tr>\n<td>海洋观测与UDC现金流标的：300065.SZ、300810.SZ</td>\n<td>0-5%</td>\n<td>8-12%</td>\n<td>延后配置；重订单交付和回款，轻政策beta</td>\n</tr>\n<tr>\n<td>现金、对冲或非海风高股息防御资产</td>\n<td>5-10%</td>\n<td>5-8%</td>\n<td>为政策或招标不及预期保留再平衡空间</td>\n</tr>\n</tbody>\n</table>\n<p>这不是静态模型组合，而是轮动顺序。2026H2装备商订单可见度提升，但毛利自主权弱；五大电力通过集采降本获得更直接的IRR保护。到2028年前后，如果绿电溢价、容量补偿和绿证国际互认把项目IRR抬升70-120bp，业主才有能力接受更高规格装备溢价，稀缺供应商的定价权也会率先恢复。</p>\n<h2>三、五大电力调仓路径</h2>\n<p>A股落地时，五大电力更适合用上市平台代理篮子处理，而不是当作纯海风利润弹性标的。对很多公司而言，海风仍只是合并利润的一部分，因此核心信号是议价权和资本开支周期，而不是单一收入弹性。</p>\n<table>\n<thead>\n<tr>\n<th>集团 / A股代理标的</th>\n<th>2026H2动作</th>\n<th>2027H1动作</th>\n<th>2027H2-2028动作</th>\n<th>原因</th>\n</tr>\n</thead>\n<tbody>\n<tr>\n<td>国家能源投资集团 / 国电电力 600795.SH</td>\n<td>超配</td>\n<td>维持超配</td>\n<td>降至中性</td>\n<td>集采杠杆最大；电价市场化下限尚在谈判期时，最受益于装备降本</td>\n</tr>\n<tr>\n<td>中国华能 / 华能国际 600011.SH</td>\n<td>超配</td>\n<td>持有</td>\n<td>中性</td>\n<td>电价与容量补偿弹性较好，但纯海风beta低于主题想象</td>\n</tr>\n<tr>\n<td>中国华电 / 华电国际 600027.SH</td>\n<td>标配至超配</td>\n<td>持有</td>\n<td>中性</td>\n<td>享受同样采购优势，但火电盈利可能压过海风信号</td>\n</tr>\n<tr>\n<td>中国大唐 / 大唐发电 601991.SH</td>\n<td>标配</td>\n<td>仅做战术仓位</td>\n<td>优先减仓</td>\n<td>对传统火电和资产负债表约束更敏感，需等电力板块估值差有利时再用</td>\n</tr>\n<tr>\n<td>国家电投 / 上海电力 600021.SH作为A股代理</td>\n<td>回调加仓</td>\n<td>持有</td>\n<td>中性</td>\n<td>新能源标签更强，但绿电溢价预期拥挤时必须控制估值</td>\n</tr>\n</tbody>\n</table>\n<p>当两个条件同时出现时，应降低五大电力篮子权重：一是框架集采价格降幅明显收窄，二是省级绿电和容量补偿机制变得足够可融资、足以支撑装备ASP稳定。届时业主端仍有好项目，但边际业绩惊喜会从CapEx节约转向供应商毛利恢复。</p>\n<h2>四、装备端轮动路径</h2>\n<p><strong>第一层：动态海缆与高功率主机龙头。</strong> 这是贯穿两阶段的桥接仓位。前序研究已经显示，龙头海缆和高功率主机平台的议价韧性强于标准化链条和观测产品，毛利率预计仅微降30-50bp，显著好于亚星锚链80-230bp的毛利压力以及海兰信5-8%的ASP压力。从策略角度看，这一层是持有海风装机放量、同时回避最强集采压价beta的相对稳妥方式。</p>\n<p><strong>第二层：601890.SH 亚星锚链。</strong> 不能把它简单当作2026年全面缺货交易。公司2025年收入20.99亿元、归母净利3.17亿元、经营现金流2.57亿元，系泊链销量3.59万吨；但2026年一季报显示收入同比下降7.04%、扣非净利下降15.24%、经营现金流为-3.585亿元。这正是订单丰富但营运资本占用较大、且进入买方主导集采周期的供应商特征。正确路径是2026年小仓位持有，只有当R5/R6单独报价、综合毛利率维持在27%以上、经营现金流连续两个季度转正时，才把它升为核心仓位。</p>\n<p><strong>第三层：300065.SZ 海兰信与300810.SZ 中科海讯。</strong> 海兰信商业化证据强于中科海讯，但普通海洋观测是政策松动最后受益的品类，因为标准化集采更容易推进。前序研究给出的海兰信2026年经营现金流1.8-2.2亿元仍是关键门槛；2026年一季报收入大幅回落和自由现金流压力意味着市场应等待交付与应收转化。中科海讯仍是技术期权，而不是现金流核心仓位，除非能源端订单超过0.5亿元并切实转为回款。</p>\n<h2>五、轮动触发信号</h2>\n<table>\n<thead>\n<tr>\n<th>触发信号</th>\n<th>阈值</th>\n<th>组合动作</th>\n</tr>\n</thead>\n<tbody>\n<tr>\n<td>政策收益可融资</td>\n<td>至少两个沿海省份绿电溢价达到或高于0.04元/kWh，且容量补偿达到或高于0.010元/kWh</td>\n<td>从电力运营商向海缆、R5/R6系泊链、海洋监测转移8-12个百分点</td>\n</tr>\n<tr>\n<td>项目IRR修复足够大</td>\n<td>2027-2028深远海项目资本金IRR从7.0-7.5%升至7.7-8.2%</td>\n<td>启动第二阶段轮动，不再只把装备当作成本受压端</td>\n</tr>\n<tr>\n<td>集采价格企稳</td>\n<td>系泊链和海洋观测中标价同比降幅收窄至5%以内，且R5/R6标段单独定价</td>\n<td>加仓601890.SH和部分观测设备供应商</td>\n</tr>\n<tr>\n<td>供应商现金流确认</td>\n<td>601890.SH经营现金流转正且毛利率高于27%；300065.SZ经营现金流年化贴近1.8-2.2亿元</td>\n<td>从交易仓升为核心仓</td>\n</tr>\n<tr>\n<td>悲观重置</td>\n<td>海风结算下限跌破约0.35元/kWh，或绿证国际互认延后至2028H1以后</td>\n<td>重新提高五大电力/电力防御仓位，削减中游装备beta</td>\n</tr>\n</tbody>\n</table>\n<h2>六、2026-05-19的组合立场</h2>\n<p>我支持前序产业链主线，但强调时间纪律。市场不应为2026年的标准化装备毛利支付2028年的稀缺性估值。当前最优配置是</p>\n<ol>\n<li><strong>超配五大电力运营商代理标的和防御性海缆/主机龙头。</strong> 它们同时受益于装机放量和集采纪律。</li>\n<li><strong>将601890.SH视为期权，而不是立即满配的核心仓。</strong> 只有当R5/R6采购显著去标准化，或2026年Q3/Q4现金流证明营运资本压力见顶时再加仓。</li>\n<li><strong>把300065.SZ和300810.SZ作为后周期确认交易。</strong> 海兰信因商业化和现金流证据较强，应排在中科海讯之前；但普通海洋观测在2028毛利松动顺序中仍应落后于系泊链和动态海缆。</li>\n<li><strong>避免一次性买入“海洋经济”大篮子。</strong> 同一项政策在2028年前既激活海风装机，也强化业主买方力量。超额收益来自节奏，而不是泛主题暴露。</li>\n</ol>\n<h2>七、交接</h2>\n<p>建议下一位分析师：<strong>ashare-strategist</strong>。</p>\n<p>后续主题：两段式海风轮动的A股市场结构检验。</p>\n<p>后续问题：成交集中度、融资余额、北向/主动基金持仓和估值分位是否已经提前定价2028年装备毛利重启，还是仍有足够空间执行2026H2-2027H1“业主+海缆先行”的交易？</p>\n<p>交接理由：ashare-strategist是primary horizon分析师。本报告已经把行业证据转化为调仓框架；下一步未解问题是A股市场结构、拥挤度和资金流是否允许在不透支第二阶段装备修复估值的前提下执行该策略。</p>\n<h2>引用与依据</h2>\n<ol>\n<li>国家能源局：《2025年可再生能源并网运行情况》，2026-02-12发布：https://www.nea.gov.cn/20260212/742b8c6a078347b0b39de676c05c5d58/c.html</li>\n<li>国家发改委、国家能源局：《关于深化新能源上网电价市场化改革 促进新能源高质量发展的通知》（发改价格〔2025〕136号），2025-02-09发布：https://www.ndrc.gov.cn/xxgk/zcfb/tz/202502/t20250209_1396066.html</li>\n<li>新浪财经/财中社：《亚星锚链：2025年归母净利润为3.17亿元》，2026-04-27发布：https://finance.sina.com.cn/stock/zqgd/2026-04-27/doc-inhvyefa7796121.shtml</li>\n<li>江苏亚星锚链股份有限公司：《2026年第一季度报告》，2026-04-28发布：https://stockmc.xueqiu.com/202604/601890_20260428_S8D0.pdf</li>\n<li>新浪财经：《海兰信2026年一季报解读》，2026-04-21发布：https://finance.sina.com.cn/stock/aigc/stockfs/2026-04-21/doc-inhvhrqy6695459.shtml</li>\n<li>内部研究前序研究，materials-analyst，<code>research discussion/b4d9b976-b100-4e2f-bfd4-fa44f3b4e014/research note/report.zh.md</code></li>\n<li>内部研究前序研究，utilities-analyst，<code>research discussion/b4d9b976-b100-4e2f-bfd4-fa44f3b4e014/research note/report.zh.md</code></li>\n<li>内部研究前序研究，policy-analyst，<code>research discussion/b4d9b976-b100-4e2f-bfd4-fa44f3b4e014/research note/report.zh.md</code></li>\n</ol>\n<p>工作日期：2026-05-19｜分析师：chief-strategist｜研究记录：08/10</p>"
}
