{
  "slug": "archive-fe98727ad434",
  "href": "/investor/reports/archive-fe98727ad434/",
  "meta": {
    "title": "CPI/FOMC前的长久期主题：量子是否是最后一块未重定价拼图？— 2026-06-10",
    "date": "2026-06-10",
    "analyst_id": "",
    "analyst_name": "",
    "tags": [
      "AI",
      "通胀",
      "宏观",
      "A股",
      "风险"
    ],
    "source": "archive-fe98727ad434",
    "source_label": "研究线程",
    "source_kind": "research_thread"
  },
  "bodyHtml": "<h1>CPI/FOMC前的长久期主题：量子是否是最后一块未重定价拼图？— 2026-06-10</h1>\n<p>截至研究所工作日2026-06-10，我对初始命题采取<strong>压力测试</strong>而非直接接受：美国2026年5月CPI定于2026年6月10日08:30 ET发布 [S1]，Kevin Warsh已于2026年5月22日宣誓就任Fed主席 [S2]，下一次FOMC会议在2026年6月16-17日举行并附带经济预测摘要 [S3]。宏观环境已经偏限制性：截至2026年6月9日，联邦基金目标区间为3.50%-3.75% [S4][S5]；截至2026年6月8日，美国10年期国债收益率为4.56% [S6]。在这个背景下，研究输入所称“量子篮子年内+69.3%”无法用我查到的公开来源独立追踪 [来源不明]；公开QTUM代理仍然强势但幅度较低，截至2026年5月31日，QTUM市价年内回报为45.98%，NAV年内回报为46.10% [S7]。</p>\n<h2>核心判断</h2>\n<p>量子并不是能完全豁免久期重定价的资产。它是一个混合体：既是长久期、高叙事增长交易，也有真实的2026年技术催化。因此，它的回撤理应小于空泛概念成长股，但不应免疫于“无降息/可能加息”的重定价。落到A股策略，我不建议在CPI和Warsh首次FOMC前追逐纯量子概念beta；更合适的是保留“政策支持且收入可见的硬科技”与“现金收益/低波动底仓”的杠铃结构。</p>\n<h2>证据地图</h2>\n<table>\n<thead>\n<tr>\n<th>证据</th>\n<th>数字/事实</th>\n<th>策略含义</th>\n</tr>\n</thead>\n<tbody>\n<tr>\n<td>研究量子篮子</td>\n<td>年内+69.3% [来源不明]</td>\n<td>可作为内部风险信号，但不能当作已验证市场事实。</td>\n</tr>\n<tr>\n<td>QTUM公开代理</td>\n<td>截至2026年5月31日，市价年内+45.98%，NAV年内+46.10% [S7]</td>\n<td>即使研究篮子不可追踪，量子代理仍显著跑赢。</td>\n</tr>\n<tr>\n<td>BQTUM指数结构</td>\n<td>当前成份82只，美元计价行业指数，下次调整日为2026年6月12日 [S8]</td>\n<td>这不是狭义纯量子指数；机器学习和多元科技暴露会稀释“纯量子”读数。</td>\n</tr>\n<tr>\n<td>半导体代理</td>\n<td>截至2026年6月8日，SMH年内回报66.10% [S9]</td>\n<td>“AI/半导体已经充分重定价”的说法过宽；局部回撤存在，但基准年内仍强。</td>\n</tr>\n<tr>\n<td>加密代理</td>\n<td>加密市场较2025年10月历史高点下跌48%，市值蒸发超过2万亿美元 [S10]</td>\n<td>纯流动性beta已经比上市量子代理更剧烈地重定价。</td>\n</tr>\n<tr>\n<td>政策利率</td>\n<td>截至2026年6月9日，Fed目标区间为3.50%-3.75% [S4][S5]</td>\n<td>更高折现率仍是低现金流主题的现实逆风。</td>\n</tr>\n<tr>\n<td>10年美债</td>\n<td>截至2026年6月8日为4.56% [S6]</td>\n<td>长久期权益因子仍暴露在利率冲击之下。</td>\n</tr>\n</tbody>\n</table>\n<h2>为什么量子确有催化</h2>\n<p>“量子优势”叙事并非空洞。IBM路线图将2026年定位为“实现首批量子优势样例”的年份，路径是把IBM量子硬件与HPC结合，并让Nighthawk处理器在最多三个120量子位模块上运行7,500门电路 [S11]。IBM还在2026年6月2日宣布，计划未来五年向量子计算投入超过100亿美元 [S12]。Google称其Quantum Echoes工作展示了可验证量子优势算法，在Willow上比全球最快超算之一运行的最佳经典算法快13,000倍 [S13]。IonQ在2026年4月14日宣布了光子互连里程碑，连接了两个囚禁离子量子系统 [S14]。</p>\n<p>这些里程碑可信，但并不自动为所有上市量子估值背书。催化最强的对象，是有可验证硬件进展、云端接入、政府或企业合同、以及资产负债表续航的公司。催化最弱的对象，是盈利尚未与量子工作负载相连的A股和离岸“概念”公司。</p>\n<h2>为什么它仍然像久期资产</h2>\n<p>对二级市场配置而言，久期属性仍然占主导。多数量子收入曲线仍在较远未来，因此股权价值对折现率变化敏感。QTUM跟踪的BQTUM本身覆盖量子和机器学习公司，而非实验室意义上的纯量子子集 [S8]。这种混合暴露在AI动量阶段可以支撑表现，但也意味着CPI/FOMC冲击会沿着同一条长久期科技通道传导。</p>\n<p>更干净的比较不是“量子对加密”。加密已较2025年10月高点回撤48% [S10]，而上市量子代理年内仍为正 [S7]。这个差距说明，量子不只是流动性beta；但也说明，如果CPI确认更久更高或加息倾斜的Fed反应函数，量子仍有剩余估值真空风险。</p>\n<h2>A股策略</h2>\n<p>我会把交易拆成三个桶</p>\n<ol>\n<li><strong>事件前不追纯概念beta。</strong> 对A股量子计算、量子通信、光子、密码安全标签而言，问题不是主题质量，而是时点。2026年6月10日CPI上行意外 [S1]，或2026年6月16-17日Warsh偏鹰沟通 [S2][S3]，会优先打击高久期、低盈利主题。</li>\n<li><strong>买实现能力，而不是只买口号。</strong> 优先关注仪器设备、低温/光子设备、精密制造、网络安全迁移、政府或企业采购相关公司。这是A股里“把催化转化为收入”的选择，而不是单纯买期权。</li>\n<li><strong>保持杠铃。</strong> 任何量子/硬科技暴露都应搭配现金流防御、高分红国企和低波动行业。目的不是放弃真实技术周期，而是在利率更高重定价时控制组合beta。</li>\n</ol>\n<h2>决策规则</h2>\n<p>我的立场是<strong>压力测试/选择性承保</strong>，不是否定。如果5月CPI温和，且2026年6月16-17日FOMC沟通更接近“维持”而非“加息”，量子篮子仍可保持领涨口袋，因为IBM、Google和IonQ给出了可信的2026年催化组合 [S11][S12][S13][S14]。如果CPI确认通胀压力，且Warsh移除宽松期权，正确动作是先削减纯概念量子beta，仅保留技术里程碑能映射到已资助需求的仓位。</p>\n<p>下一张研究记录缺的不是另一层宏观叠加，而是催化质量审计：哪些量子公司和A股映射标的的里程碑有可能转化为2026-2027年收入，哪些只是借用了“量子优势”标签？</p>\n<p>页脚：前序研究，首席策略师，工作日2026-06-10。缺失的工作区文件（<code>研究档案</code>、<code>研究档案</code>、此前研究记录报告）已根据对话上下文重建。</p>\n<h2>资料来源 / Sources</h2>\n<p>[S1] U.S. Bureau of Labor Statistics, Schedule of Releases for the Consumer Price Index — https://www.bls.gov/schedule/news_release/cpi.htm</p>\n<p>[S2] Federal Reserve Board, Kevin Warsh takes oath of office as chairman and a member of the Board of Governors of the Federal Reserve System, and the Federal Open Market Committee unanimously selects Warsh as its chairman — https://www.federalreserve.gov/newsevents/pressreleases/other20260522a.htm</p>\n<p>[S3] Federal Reserve Board, Meeting calendars and information — https://www.federalreserve.gov/monetarypolicy/fomccalendars.htm</p>\n<p>[S4] FRED, Federal Funds Target Range - Lower Limit (DFEDTARL) — https://fred.stlouisfed.org/series/DFEDTARL</p>\n<p>[S5] FRED, Federal Funds Target Range - Upper Limit (DFEDTARU) — https://fred.stlouisfed.org/series/DFEDTARU</p>\n<p>[S6] FRED, Market Yield on U.S. Treasury Securities at 10-Year Constant Maturity (DGS10) — https://fred.stlouisfed.org/series/DGS10</p>\n<p>[S7] Defiance ETFs, QTUM: The Next Generation Quantum Computing &amp; AI ETF — https://www.defianceetfs.com/qtum/</p>\n<p>[S8] MarketVector, BlueStar Machine Learning and Quantum Computing Index (BQTUM) — https://www.marketvector.com/indexes/sector/bluestar-machine-learning-and-quantum-computing</p>\n<p>[S9] Yahoo Finance, VanEck Semiconductor ETF (SMH) Performance History — https://finance.yahoo.com/quote/SMH/performance/</p>\n<p>[S10] Seeking Alpha, Crypto market loses over $2T from peak — https://seekingalpha.com/news/4600611-crypto-market-loses-over-2t-from-peak</p>\n<p>[S11] IBM, IBM Quantum Roadmap — https://www.ibm.com/roadmaps/quantum/</p>\n<p>[S12] IBM Newsroom, IBM Commits More Than 0 Billion to Quantum Computing — https://newsroom.ibm.com/2026-06-02-ibm-commits-more-than-10-billion-to-quantum-computing%2C-funding-its-roadmap-from-todays-leading-systems-to-the-worlds-first-fault-tolerant-quantum-computers</p>\n<p>[S13] Google Blog, The Quantum Echoes algorithm breakthrough — https://blog.google/innovation-and-ai/technology/research/quantum-echoes-willow-verifiable-quantum-advantage/</p>\n<p>[S14] IonQ, IonQ Achieves First Photonic Interconnect Milestone for Networked Commercial Quantum Systems — https://www.ionq.com/news/ionq-achieves-key-photonic-interconnect-milestone-demonstrating-networked-quantum-systems-using-entanglement</p>"
}
