{
  "slug": "archive-c8216da0e667",
  "href": "/investor/reports/archive-c8216da0e667/",
  "meta": {
    "title": "目标价与评级",
    "date": "2026-07-20",
    "analyst_id": "",
    "analyst_name": "",
    "tags": [
      "AI",
      "通胀",
      "宏观",
      "A股",
      "风险"
    ],
    "source": "archive-c8216da0e667",
    "source_label": "研究档案",
    "source_kind": "archive"
  },
  "bodyHtml": "<p>研究对象: 301206.SZ</p>\n<h1>目标价与评级</h1>\n<h2>一、定价口径</h2>\n<p>本报告唯一研究对象为 <code>301206.SZ</code>，证券简称三元生物，公司全称山东三元生物科技股份有限公司[S1]。本步骤已读取本地前序 Markdown 文件：<code>研究档案</code>、<code>研究档案</code>、<code>研究档案</code>、<code>研究档案</code>、<code>研究档案</code>、<code>研究档案</code>、<code>研究档案</code>、<code>研究档案</code>、<code>研究档案</code>[自测算：本地文件读取记录]。当前价格采用 2026-07-20 重新抓取的东方财富行情接口[自测算：当前工作流日期]，最新价为 23.46 元/股、PE-TTM 为 45.48 倍、PB 为 1.14 倍、总市值为 4,746,560,922 元、流通市值为 3,056,266,116 元[S7]。</p>\n<p>前序盈利预测基准情形预计 2026E、2027E、2028E 归母净利润分别为 91.91 百万元、105.95 百万元、132.89 百万元，EPS 分别为 0.45 元/股、0.52 元/股、0.66 元/股[自测算：输入来自 <code>研究档案</code>，股本分母为 202,325,700 股，股本输入来自 S2]。前序估值分析给出的综合合理价值中枢为 21.44 元/股，综合合理价值区间为 18.67-24.32 元/股[自测算：输入来自 <code>研究档案</code>]。本报告以综合估值中枢作为 12 个月目标价主锚，以 2028E EPS 的折价 PE 作为 18 个月滚动目标价校验[自测算]。</p>\n<h2>二、12 个月目标价推导</h2>\n<p>12 个月目标价采用综合估值法：DCF、PE、PB、EV/EBITDA 的权重分别为 35%、25%、15%、25%[自测算]。该方法保留前序估值对净现金资产、低 ROE、阿洛酮糖成长性和主业 EBITDA 的综合约束[自测算]。</p>\n<table>\n<thead>\n<tr>\n<th>方法</th>\n<th>单项估值</th>\n<th>权重</th>\n<th>加权贡献</th>\n<th>关键含义</th>\n</tr>\n</thead>\n<tbody>\n<tr>\n<td>DCF</td>\n<td>21.23 元/股[自测算]</td>\n<td>35%[自测算]</td>\n<td>7.43 元/股[自测算：21.23 × 35%]</td>\n<td>经营自由现金流恢复仍慢，非经营性金融资产贡献较大[自测算]</td>\n</tr>\n<tr>\n<td>PE</td>\n<td>19.90 元/股[自测算]</td>\n<td>25%[自测算]</td>\n<td>4.98 元/股[自测算：19.90 × 25%]</td>\n<td>采用 2027E EPS 0.5237 元/股与 38.00 倍目标 PE[自测算]</td>\n</tr>\n<tr>\n<td>PB</td>\n<td>21.32 元/股[自测算]</td>\n<td>15%[自测算]</td>\n<td>3.20 元/股[自测算：21.32 × 15%]</td>\n<td>2027E BVPS 为 21.32 元/股，目标 PB 为 1.00 倍[自测算]</td>\n</tr>\n<tr>\n<td>EV/EBITDA</td>\n<td>23.33 元/股[自测算]</td>\n<td>25%[自测算]</td>\n<td>5.83 元/股[自测算：23.33 × 25%]</td>\n<td>2027E 经营 EBITDA 为 163.21 百万元，目标 EV/EBITDA 为 11.00 倍，并加回非经营性金融资产净额[自测算]</td>\n</tr>\n<tr>\n<td>综合中枢</td>\n<td>21.44 元/股[自测算：7.43 + 4.98 + 3.20 + 5.83]</td>\n<td>100%[自测算]</td>\n<td>21.44 元/股[自测算]</td>\n<td>作为 12 个月目标价的未四舍五入口径[自测算]</td>\n</tr>\n</tbody>\n</table>\n<p>12 个月目标价取 21.50 元/股[自测算：21.44 元/股四舍五入并保留交易可读性]。相对当前 23.46 元/股，12 个月目标价对应空间为 -8.35%[自测算：21.50 ÷ 23.46 - 1；当前价输入来自 S7]。</p>\n<h2>三、18 个月目标价推导</h2>\n<p>18 个月目标价采用滚动盈利口径：以 2028E EPS 0.66 元/股作为远期盈利锚，给予 34.00 倍目标 PE，得到 22.44 元/股，并取 22.50 元/股作为可执行目标价[自测算：0.66 × 34.00]。34.00 倍目标 PE 低于当前 PE-TTM 45.48 倍[S7]，原因是公司 2025 年加权平均 ROE 仅 2.09%[S1]、经营现金流质量仍待改善；但该倍数高于多数传统糖醇同业估值锚，以反映 D-阿洛酮糖国内准入和年产 2 万吨阿洛酮糖项目投产带来的成长期权[S3][S4][自测算]。</p>\n<table>\n<thead>\n<tr>\n<th>项目</th>\n<th>数值</th>\n<th>说明</th>\n</tr>\n</thead>\n<tbody>\n<tr>\n<td>2028E EPS</td>\n<td>0.66 元/股[自测算]</td>\n<td>前序盈利预测基准情形，分母采用 202,325,700 股[S2][自测算]</td>\n</tr>\n<tr>\n<td>18 个月目标 PE</td>\n<td>34.00 倍[自测算]</td>\n<td>较当前 PE-TTM 45.48 倍折价，反映低 ROE 与现金流约束[S7][S1][自测算]</td>\n</tr>\n<tr>\n<td>未四舍五入目标价</td>\n<td>22.44 元/股[自测算：0.66 × 34.00]</td>\n<td>2028E EPS × 目标 PE[自测算]</td>\n</tr>\n<tr>\n<td>18 个月目标价</td>\n<td>22.50 元/股[自测算]</td>\n<td>交易可读性取整[自测算]</td>\n</tr>\n<tr>\n<td>相对当前价空间</td>\n<td>4.09%[自测算：22.50 ÷ 23.46 - 1]</td>\n<td>当前价为 23.46 元/股[S7]</td>\n</tr>\n</tbody>\n</table>\n<h2>四、下行风险、止损与风险收益比</h2>\n<p>止损位设为 18.70 元/股[自测算]。该价格接近前序综合估值区间下沿 18.67 元/股[自测算：输入来自 <code>研究档案</code>]，也对应“功能糖放量未达基准、糖醇出口压力持续、估值从成长预期回到资产支撑”的防守线[自测算；依据 S1、S4]。</p>\n<table>\n<thead>\n<tr>\n<th>指标</th>\n<th>数值</th>\n<th>推导</th>\n</tr>\n</thead>\n<tbody>\n<tr>\n<td>当前价</td>\n<td>23.46 元/股[S7]</td>\n<td>东方财富行情接口取数[S7]</td>\n</tr>\n<tr>\n<td>12 个月目标价</td>\n<td>21.50 元/股[自测算]</td>\n<td>综合估值中枢 21.44 元/股四舍五入[自测算]</td>\n</tr>\n<tr>\n<td>18 个月目标价</td>\n<td>22.50 元/股[自测算]</td>\n<td>2028E EPS 0.66 元/股 × 34.00 倍 PE[自测算]</td>\n</tr>\n<tr>\n<td>止损位</td>\n<td>18.70 元/股[自测算]</td>\n<td>贴近综合估值区间下沿 18.67 元/股[自测算]</td>\n</tr>\n<tr>\n<td>12 个月目标空间</td>\n<td>8.35%[自测算：21.50 ÷ 23.46 - 1]</td>\n<td>当前价输入来自 S7</td>\n</tr>\n<tr>\n<td>18 个月目标空间</td>\n<td>4.09%[自测算：22.50 ÷ 23.46 - 1]</td>\n<td>当前价输入来自 S7</td>\n</tr>\n<tr>\n<td>止损下行空间</td>\n<td>20.29%[自测算：18.70 ÷ 23.46 - 1]</td>\n<td>当前价输入来自 S7</td>\n</tr>\n<tr>\n<td>风险收益比</td>\n<td>0.41:1[自测算：-8.35% ÷ 20.29%]</td>\n<td>按 12 个月目标回报除以止损下行空间；若按长仓正向收益口径，当前正向收益为 0.00%，风险收益比为 0.00:1[自测算]</td>\n</tr>\n</tbody>\n</table>\n<h2>五、正式评级</h2>\n<p>正式评级：neutral（中性）[自测算]。</p>\n<p>评级含义是：当前 23.46 元/股价格已经高于 12 个月目标价 21.50 元/股，并高于前序综合估值中枢 21.44 元/股[S7][自测算]。若 2026 年半年报验证功能糖收入、综合毛利率和经营现金流改善，评级可上调至 buy（买入）；若功能糖放量慢于模型、糖醇出口继续承压或股价跌破 18.70 元/股止损位，评级应下调至 sell（卖出）[自测算；依据 S1、S2、S4]。</p>\n<h2>六、评级理由（三句话）</h2>\n<p>第一，阿洛酮糖是最重要的向上期权，D-阿洛酮糖于 2025-07-02 作为新食品原料通过安全性评估材料审查，公司年产 2 万吨阿洛酮糖项目于 2026-06-03 全线投产，支撑 2026E-2028E EPS 从 0.45 元/股提升至 0.66 元/股的基准路径[S3][S4][自测算]。第二，当前 23.46 元/股价格已经隐含较多基准情景，12 个月目标价 21.50 元/股对应 -8.35% 空间，18 个月目标价 22.50 元/股对应 -4.09% 空间[S7][自测算]。第三，止损位 18.70 元/股对应 -20.29% 下行，12 个月风险收益比为 -0.41:1，因此在半年报和功能糖利润质量验证前，neutral（中性）比 buy（买入）更合适[自测算]。</p>\n<h2>资料来源 / Sources</h2>\n<p>[S1] 山东三元生物科技股份有限公司, 《2025 年年度报告》 — https://pdf.dfcfw.com/pdf/H2_AN202604281821688061_1.pdf</p>\n<p>[S2] 山东三元生物科技股份有限公司, 《2026 年第一季度报告》 — https://pdf.dfcfw.com/pdf/H2_AN202604281821688113_1.pdf</p>\n<p>[S3] 国家卫生健康委, 《关于D-阿洛酮糖等20种“三新食品”的公告》 — https://zwfw.nhc.gov.cn/kzx/tzgg/sptjjxpzsp_224/202507/t20250702_3106.html</p>\n<p>[S4] 山东三元生物科技股份有限公司, 《关于年产2万吨阿洛酮糖项目投产的公告》 — https://money.finance.sina.com.cn/corp/view/vCB_AllBulletinDetail.php?id=12371115&amp;stockid=301206</p>\n<p>[S7] 东方财富, 沪深 A 股行情估值 API — https://push2.eastmoney.com/api/qt/ulist.np/get?fltt=2&amp;fields=f12,f14,f2,f3,f4,f5,f6,f17,f18,f20,f21,f9,f23,f100,f115,f116,f117,f162&amp;secids=0.301206</p>"
}
