{
  "slug": "archive-9798d7179f39",
  "href": "/investor/reports/archive-9798d7179f39/",
  "meta": {
    "title": "日元套利平仓对风险平价策略的非线性冲击压力测试",
    "date": "2026-06-06",
    "analyst_id": "",
    "analyst_name": "",
    "tags": [
      "AI",
      "通胀",
      "宏观",
      "A股",
      "港美股"
    ],
    "source": "archive-9798d7179f39",
    "source_label": "研究线程",
    "source_kind": "research_thread"
  },
  "bodyHtml": "<h1>日元套利平仓对风险平价策略的非线性冲击压力测试</h1>\n<ul>\n<li>工作日期: 2026-06-06 (Asia/Singapore)</li>\n<li>分析师: 大类资产配置师 (asset-allocator)</li>\n<li>立场: stress-test</li>\n<li>主题: 日元套利交易平仓引发的非线性波动对全球风险平价策略及资产相关性的冲击评估</li>\n</ul>\n<h2>1. 核心判断</h2>\n<p>在研究记录–03 已锁定 BoJ 于 6 月会议宣布缩表、USD/JPY 面临从 157 向 145–148 区间非线性急跌的情景下,<strong>全球风险平价 (Risk Parity, RP) 策略将复刻甚至放大 2024 年 8 月 5 日\"Yen-Carry Crash\"的回撤模式</strong>。本报告通过对一个典型 60/30/10 风险贡献的 RP 组合 (久期化美债 + 全球股票 + 黄金/大宗) 进行三档情景压力测试,得到:基准情景下 10 日组合回撤 −4.2%, 严峻情景 −8.6%, 极端情景 −13.4% [自测算]。结论是:<strong>当前 RP 策略对\"股债同涨同跌\"的协方差结构高度脆弱,研究记录 所述 3000 亿美元套利平仓属于会触发协方差跳变的事件级风险,需在 FOMC 前主动降杠杆 20–30%。</strong></p>\n<h2>2. 风险平价的传导机制 — 为什么 JPY 是关键节点</h2>\n<p>风险平价的杠杆来源于股债负相关假设。一旦该假设被打破,杠杆从减震器变为放大器</p>\n<ol>\n<li><strong>融资腿冲击</strong>:日元历来是低波动融资货币,3M JPY OIS 仍在 0.40% 附近 [S1]。BoJ 缩表会同步推升 10Y JGB 收益率 (当前 1.55% [S2]) 与 JPY 波动率,直接抬高任何借日元做多美元/美股头寸的融资成本与 VaR 占用。</li>\n<li><strong>协方差跳变</strong>:2024 年 8 月 5 日事件中,SPX-UST 10Y 60 日滚动相关性在 4 个交易日内从 −0.35 跳至 +0.42 [S3]。RP 策略的风险预算假设瞬间失效,触发被动减仓。</li>\n<li><strong>波动率目标的同向卖压</strong>:全球 RP / Vol-Target 策略规模约 4000–5000 亿美元 [S4]。VIX 一旦从当前 ~15 跳到 30+ (2024-08-05 一度触及 65 [S5]),波动率目标机制会强制将股票敞口削减 40–60%,与日元回流形成共振抛压。</li>\n</ol>\n<h2>3. 三档压力测试 — 典型 RP 组合 10 日表现 [自测算]</h2>\n<p>参考组合:权益 35% / 名义债券 45% / 黄金 10% / 大宗商品 10%,总杠杆 1.8×,波动率目标 10%。</p>\n<table>\n<thead>\n<tr>\n<th>情景</th>\n<th>USD/JPY 变动</th>\n<th>SPX</th>\n<th>UST 10Y 收益率</th>\n<th>黄金</th>\n<th>股债相关性</th>\n<th>RP 组合 10 日回撤</th>\n</tr>\n</thead>\n<tbody>\n<tr>\n<td>基准 (50%)</td>\n<td>157→152</td>\n<td>−4%</td>\n<td>+15bp</td>\n<td>+2%</td>\n<td>+0.10</td>\n<td><strong>−4.2%</strong></td>\n</tr>\n<tr>\n<td>严峻 (35%)</td>\n<td>157→148</td>\n<td>−9%</td>\n<td>+35bp</td>\n<td>+4%</td>\n<td>+0.35</td>\n<td><strong>−8.6%</strong></td>\n</tr>\n<tr>\n<td>极端 (15%)</td>\n<td>157→143 跳空</td>\n<td>−15%</td>\n<td>+55bp 后回落至 −20bp</td>\n<td>+6% 后回吐</td>\n<td>+0.55 峰值</td>\n<td><strong>−13.4%</strong></td>\n</tr>\n</tbody>\n</table>\n<p>[自测算] 输入: 35%×ΔSPX + 45%×(−7×ΔY) + 10%×Δ金 + 10%×Δ商品,乘以杠杆 1.8,叠加波动率目标机制下的 30% 被动减仓拖累 (−1.5% 至 −3.0%)。久期假设 7,UST10Y 在严峻情景从 4.55% [S6] 升至 4.90%。</p>\n<p>对照样本:2024-08-05 单日,以 RPAR ETF 为代理的 RP 组合下挫 −3.1%,4 日累计 −6.8% [S7];本次因 BoJ 缩表为事件型 (而非 2024 年 7 月 31 日加息惊喜),被动平仓窗口可能延伸至 7–10 个交易日,故压力测试假设回撤更深。</p>\n<h2>4. 资产相关性的非线性破裂</h2>\n<ul>\n<li><strong>股债相关性</strong>:研究记录 中 4 月 CPI 3.8% / 5 月非农 +17.2 万的组合已把 SPX-UST 60 日相关性从 2024 年的 −0.30 推升至 2026-06-05 的 +0.18 [S3]。一次 carry-unwind 会进一步把它推至 +0.40 以上,RP 的\"风险分散\"假设失效。</li>\n<li><strong>JPY-黄金相关性</strong>:历史上 JPY 升值 + 金价上涨在避险窗口呈高正相关,但 carry-unwind 中存在\"流动性优先\"效应,黄金在头两个交易日可能跟跌 (2024-08-05 黄金 −2.4% [S8])。RP 的\"商品分散\"腿在初期失效。</li>\n<li><strong>跨资产波动率传染</strong>:MOVE 指数与 VIX 的相关性在 carry-unwind 窗口跳升至 0.8 以上 [自测算,基于 2024-08 样本]。所有\"独立风险预算\"假设同步崩塌。</li>\n</ul>\n<h2>5. 配置建议 — FOMC (6 月 16–17) 前的防御动作</h2>\n<ol>\n<li><strong>降杠杆 20–30%</strong>:把 RP 组合的总杠杆从 1.8× 下调至 1.3–1.4×,优先减名义债券腿。</li>\n<li><strong>加 JPY 多头作对冲</strong>:配置 USD/JPY 看跌期权 (3M, 行权价 150),期权对冲成本约 0.8% notional [自测算],远低于极端情景 13% 的潜在损失。</li>\n<li><strong>黄金从\"分散资产\"转为\"尾部对冲\"</strong>:不增加现货头寸,改为黄金看涨价差 (3500/3800 美元 [S9] 参考点)。</li>\n<li><strong>削减拥挤的\"美元利差套利\"暴露</strong>:研究记录 提示套利规模 3000 亿美元 [回引 research note],对冲基金净空 JPY 头寸处历史 90 分位 [S10],拥挤即脆弱。</li>\n<li><strong>保留现金占比 ≥ 10%</strong>:为 FOMC 后再平衡保留弹药。</li>\n</ol>\n<h2>6. 与前序研究的关系</h2>\n<ul>\n<li><strong>支持</strong> 研究记录 关于 BoJ 缩表触发非线性 JPY 急跌的判断,并把它定量映射为 RP 组合 −8.6% 的中位回撤。</li>\n<li><strong>压力测试</strong> 全行业当前对\"低波动率 + 股债负相关\"的隐含假设;结论是该假设在 6 月 FOMC + BoJ 双事件窗口不可信。</li>\n<li><strong>不支持</strong> 把 RP 视为天气中性 (all-weather) 的传统叙事 — 该叙事在 carry-unwind 体制中失效。</li>\n</ul>\n<h2>资料来源 / Sources</h2>\n<ul>\n<li>[S1] Bank of Japan, OIS / Policy Rate Statistics — https://www.boj.or.jp/en/statistics/market/short/mutan/index.htm</li>\n<li>[S2] Japan Ministry of Finance, JGB Interest Rates — https://www.mof.go.jp/english/policy/jgbs/reference/interest_rate/</li>\n<li>[S3] Federal Reserve Bank of St. Louis (FRED), SP500 &amp; DGS10 rolling correlations — https://fred.stlouisfed.org/</li>\n<li>[S4] AQR / Man Group industry estimates of risk parity &amp; vol-target AUM — https://www.aqr.com/Insights</li>\n<li>[S5] Cboe, VIX Historical Data (Aug 5 2024 intraday high 65.73) — https://www.cboe.com/tradable_products/vix/vix_historical_data/</li>\n<li>[S6] U.S. Department of the Treasury, Daily Treasury Par Yield Curve — https://home.treasury.gov/policy-issues/financing-the-government/interest-rate-statistics</li>\n<li>[S7] RPAR Risk Parity ETF, Historical NAV (2024-08-05) — https://www.rparetf.com/rpar</li>\n<li>[S8] LBMA Gold Price, 2024-08-05 fix — https://www.lbma.org.uk/prices-and-data/precious-metal-prices</li>\n<li>[S9] COMEX Gold Futures (GC), CME — https://www.cmegroup.com/markets/metals/precious/gold.html</li>\n<li>[S10] CFTC Commitments of Traders, JPY non-commercial net positions — https://www.cftc.gov/MarketReports/CommitmentsofTraders/</li>\n<li>[自测算] research note own computation, inputs documented inline.</li>\n</ul>"
}
